punditkit/__init__.py
punditkit/backend.py
punditkit/interface.py
punditkit/mlxtend_plotting.py
punditkit/modelling.py
punditkit/run.py
punditkit-0.0.2.dist-info/LICENSE
punditkit-0.0.2.dist-info/METADATA
punditkit-0.0.2.dist-info/WHEEL
punditkit-0.0.2.dist-info/entry_points.txt
punditkit-0.0.2.dist-info/top_level.txt
punditkit-0.0.2.dist-info/RECORD
