Metadata-Version: 2.1
Name: punditkit
Version: 0.0.2
Summary: PunditKit: A GUI for Scikit-Learn Models
Home-page: https://github.com/JackyP/punditkit
Author: Jacky Poon
Author-email: jackypn@gmail.com
License: UNKNOWN
Platform: UNKNOWN
Classifier: Programming Language :: Python :: 3
Classifier: License :: OSI Approved :: GNU General Public License v3 or later (GPLv3+)
Classifier: Operating System :: OS Independent
Requires-Dist: pandas (>=0.24.2)
Requires-Dist: scikit-learn (>=0.20.3)
Requires-Dist: streamlit (==0.53.0)
Requires-Dist: matplotlib (>=3.0.3)
Requires-Dist: yellowbrick (>=1.0.1)
Requires-Dist: pdpbox (>=0.2.0)
Requires-Dist: seaborn (>=0.9.0)
Requires-Dist: lime (>=0.1.1.37)
Requires-Dist: mlxtend (==0.17.0)
